{
  "install-success": true,
  "install_time": 5.624817848205566,
  "post-install-success": true,
  "lockfile": {
    "name": "regjsparser",
    "version": "0.7.0",
    "lockfileVersion": 2,
    "requires": true,
    "packages": {
      "": {
        "name": "regjsparser",
        "version": "0.7.0",
        "license": "BSD-2-Clause",
        "dependencies": {
          "jsesc": "~0.5.0"
        },
        "bin": {
          "regjsparser": "bin/parser"
        },
        "devDependencies": {
          "regenerate": "~1.0.1",
          "unicode-11.0.0": "^0.7.8"
        }
      },
      "node_modules/jsesc": {
        "version": "0.5.0",
        "integrity": "sha1-597mbjXW/Bb3EP6R1c9p9w8IkR0=",
        "bin": {
          "jsesc": "bin/jsesc"
        }
      },
      "node_modules/regenerate": {
        "version": "1.0.1",
        "resolved": "https://registry.npmjs.org/regenerate/-/regenerate-1.0.1.tgz",
        "integrity": "sha1-OQVHbyooBE6+cMR+Ck0R2dF7dCQ=",
        "dev": true
      },
      "node_modules/unicode-11.0.0": {
        "version": "0.7.8",
        "resolved": "https://registry.npmjs.org/unicode-11.0.0/-/unicode-11.0.0-0.7.8.tgz",
        "integrity": "sha512-O/7kwPxe1ZOiwbLr4/OleBnUDwDRldjubW5SqcQvz1b2EMPp5mQotOdf4L1z/5CNzSDVmWM9cFmseOI6L8vb6g==",
        "deprecated": "Use @unicode/unicode-11.0.0 instead.",
        "dev": true
      }
    },
    "dependencies": {
      "jsesc": {
        "version": "0.5.0"
      },
      "regenerate": {
        "version": "1.0.1",
        "resolved": "https://registry.npmjs.org/regenerate/-/regenerate-1.0.1.tgz",
        "integrity": "sha1-OQVHbyooBE6+cMR+Ck0R2dF7dCQ=",
        "dev": true
      },
      "unicode-11.0.0": {
        "version": "0.7.8",
        "resolved": "https://registry.npmjs.org/unicode-11.0.0/-/unicode-11.0.0-0.7.8.tgz",
        "integrity": "sha512-O/7kwPxe1ZOiwbLr4/OleBnUDwDRldjubW5SqcQvz1b2EMPp5mQotOdf4L1z/5CNzSDVmWM9cFmseOI6L8vb6g==",
        "dev": true
      }
    }
  }
}