{
  "install-success": true,
  "install_time": 3.1865572929382324,
  "post-install-success": true,
  "installed_deps": {
    "node_modules/kleur": {
      "version": "3.0.3",
      "resolved": "https://registry.npmjs.org/kleur/-/kleur-3.0.3.tgz",
      "integrity": "sha512-eTIzlVOSUR+JxdDFepEYcBMtZ9Qqdef+rnzWdRZuMbOywu5tO2w2N7rqjoANZ5k9vywhL6Br1VRjUIgTQx4E8w==",
      "engines": {
        "node": ">=6"
      }
    },
    "node_modules/sisteransi": {
      "version": "1.0.5",
      "resolved": "https://registry.npmjs.org/sisteransi/-/sisteransi-1.0.5.tgz",
      "integrity": "sha512-bLGGlR1QxBcynn2d5YmDX4MGjlZvy2MRBDRNHLJ8VI6l6+9FUiyTFNJ0IveOSP0bcXgVDPRcfGqA0pjaqUpfVg=="
    }
  }
}