{
  "install-success": false,
  "install_time": 11.444229125976562,
  "error": {
    "stage": "install",
    "command": "npm install --rosette --ignore-scripts",
    "retcode": 1,
    "stdout": "0 / 1\n100 / 1174\n200 / 1074\n300 / 977\n400 / 877\n500 / 777\n600 / 677\n700 / 577\n800 / 477\n900 / 377\n1000 / 277\n1100 / 177\n1200 / 77\n1300 / 43\n1400 / 73\n1500 / 13\nSending query to rosette: /tmp/tmp-40960-6p6vL20PoO44\nGot: /tmp/tmp-40960-QjHlNVmCnLWJ\nDecoding Rosette answer: [object Object]\n",
    "stderr": "npm ERR! Failed to solve constraints :(\n\nnpm ERR! A complete log of this run can be found in:\nnpm ERR!     /home/donald/.npm/_logs/2021-10-25T03_59_01_745Z-debug.log\n"
  }
}