{
  "install-success": true,
  "install_time": 2.6804752349853516,
  "post-install-success": true,
  "installed_deps": {
    "node_modules/isobject": {
      "version": "3.0.1",
      "resolved": "https://registry.npmjs.org/isobject/-/isobject-3.0.1.tgz",
      "integrity": "sha1-TkMekrEalzFjaqH5yNHMvP2reN8=",
      "engines": {
        "node": ">=0.10.0"
      }
    },
    "node_modules/map-visit": {
      "version": "1.0.0",
      "resolved": "https://registry.npmjs.org/map-visit/-/map-visit-1.0.0.tgz",
      "integrity": "sha1-7Nyo8TFE5mDxtb1B8S80edmN+48=",
      "dependencies": {
        "object-visit": "^1.0.0"
      },
      "engines": {
        "node": ">=0.10.0"
      }
    },
    "node_modules/object-visit": {
      "version": "1.0.1",
      "resolved": "https://registry.npmjs.org/object-visit/-/object-visit-1.0.1.tgz",
      "integrity": "sha1-95xEk68MU3e1n+OdOV5BBC3QRbs=",
      "dependencies": {
        "isobject": "^3.0.0"
      },
      "engines": {
        "node": ">=0.10.0"
      }
    }
  }
}